vandc/__init__.py
vandc/cli.py
vandc/fetch.py
vandc/util.py
vandc/writer.py
vandc-0.1.9.dist-info/WHEEL
vandc-0.1.9.dist-info/entry_points.txt
vandc-0.1.9.dist-info/METADATA
vandc-0.1.9.dist-info/RECORD
