Metadata-Version: 2.3
Name: vandc
Version: 0.1.9
Summary: Wandb but without any features
Author: Christopher Gadzinski
Author-email: Christopher Gadzinski <me@cgad.ski>
Requires-Dist: human-id>=0.2.0
Requires-Dist: loguru>=0.7
Requires-Dist: numpy
Requires-Dist: pandas
Requires-Dist: pyperclip>=1.11.0
Requires-Dist: qqdm>=0.0.7
Requires-Dist: questionary>=2.1.0
Requires-Dist: torch
Requires-Dist: seaborn>=0.13.2 ; extra == 'demo'
Requires-Python: >=3.8
Provides-Extra: demo
